setup.py
synapse_pay_rest/__init__.py
synapse_pay_rest/client.py
synapse_pay_rest/http_client.py
synapse_pay_rest.egg-info/PKG-INFO
synapse_pay_rest.egg-info/SOURCES.txt
synapse_pay_rest.egg-info/dependency_links.txt
synapse_pay_rest.egg-info/requires.txt
synapse_pay_rest.egg-info/top_level.txt
synapse_pay_rest/api/HelperFunctions.py
synapse_pay_rest/api/Nodes.py
synapse_pay_rest/api/Trans.py
synapse_pay_rest/api/Users.py
synapse_pay_rest/api/__init__.py