Metadata-Version: 1.1
Name: synapse-pay-rest
Version: 0.0.26
Summary: SynapsePay Rest Python Library
Home-page: https://github.com/synapsepay/SynapsePayRest-Python
Author: SynapsePay LLC
Author-email: help@synapsepay.com
License: MIT
Keywords: SynapsePay v3 Rest API
Platform: UNKNOWN
Classifier: Development Status :: 3 - Alpha
Classifier: Intended Audience :: Developers
Classifier: License :: OSI Approved :: MIT License
Classifier: Programming Language :: Python :: 2.7
